[
  {
    "id": "UA-2026-03-26-010121-a",
    "_raw_id": "809c4a2a0dd94edbada96fea12d92318",
    "title": "ДК 021:2015 - 31150000-2 - Баласти для розрядних ламп чи трубок (Гібридний інвертор та акумуляторні батареї)",
    "org": "АКЦІОНЕРНЕ ТОВАРИСТВО ПОЛТАВАОБЛЕНЕРГО",
    "source": "prozorro",
    "platform": "prozorro",
    "type": "BESS",
    "amount": 13000000.0,
    "currency": "UAH",
    "deadline": "2026-04-08",
    "cpvs": [
      "31150000-2"
    ],
    "cpv": "31150000-2",
    "status": "urgent",
    "url": "https://prozorro.gov.ua/tender/809c4a2a0dd94edbada96fea12d92318",
    "is_new": true,
    "score": 85,
    "fetched_at": "2026-04-08T11:12:22.234210"
  },
  {
    "id": "UA-2026-03-20-009920-a",
    "_raw_id": "aebdb5ec5893401faea13af58d9813ae",
    "title": "ДК 021:2015 31150000-2 Баласти для розрядних ламп чи трубок (комплект: сонячний інвертор Deye SUN-20K-SG05LP3-EU-SM2, 20 кВт, 3-фазний або «еквівалент»;  акумуляторна батарея Deye SE-G5.1Pro-B LiFePO4 51,2V/100AH, 5120W*h або «еквівалент») для Лебединського закладу загальної середньої освіти І-ІІІ ступенів № 7 Лебединської міської ради Сумської області\n",
    "org": "Управління освіти, молоді та спорту виконавчого комітету Лебединської міської ради",
    "source": "prozorro",
    "platform": "prozorro",
    "type": "BESS",
    "amount": 294000.0,
    "currency": "UAH",
    "deadline": "2026-03-30",
    "cpvs": [
      "31150000-2"
    ],
    "cpv": "31150000-2",
    "status": "active",
    "url": "https://prozorro.gov.ua/tender/aebdb5ec5893401faea13af58d9813ae",
    "is_new": false,
    "score": 80,
    "fetched_at": "2026-03-27T11:06:05.363033"
  },
  {
    "id": "UA-2026-03-31-000288-a",
    "_raw_id": "d8e947ccd6ec4d8289537661258ae153",
    "title": "Комплект безперебійного живлення (гібридний інвертор та акумулятор)",
    "org": "Головне управління Державної служби України з надзвичайних ситуацій у Запорізькій області",
    "source": "prozorro",
    "platform": "prozorro",
    "type": "BESS",
    "amount": 406991.57,
    "currency": "UAH",
    "deadline": "2026-04-08",
    "cpvs": [
      "31150000-2"
    ],
    "cpv": "31150000-2",
    "status": "urgent",
    "url": "https://prozorro.gov.ua/tender/d8e947ccd6ec4d8289537661258ae153",
    "is_new": false,
    "score": 80,
    "fetched_at": "2026-04-08T06:04:21.657988"
  },
  {
    "id": "UA-2026-04-08-002340-a",
    "_raw_id": "a5697823dd334baa9e999c85f8c2d2ad",
    "title": "Гібридний інвертор DEYE SUN-30K-SG02HP3-EU-AM3 30kW 230V 3 MPPT Wi-Fi Трифазний (DEYE SUN-30K-SG02HP3-EU-AM3) (код ДК 021:2015: 31150000-2 - Баласти для розрядних ламп чи трубок)",
    "org": "Відділ освіти Куяльницької сільської ради Подільського району Одеської області",
    "source": "prozorro",
    "platform": "prozorro",
    "type": "Inverter",
    "amount": 155000.0,
    "currency": "UAH",
    "deadline": "2026-04-13",
    "cpvs": [
      "31150000-2"
    ],
    "cpv": "31150000-2",
    "status": "active",
    "url": "https://prozorro.gov.ua/tender/a5697823dd334baa9e999c85f8c2d2ad",
    "is_new": true,
    "score": 80,
    "fetched_at": "2026-04-08T11:40:36.864625"
  },
  {
    "id": "UA-2026-03-20-006846-a",
    "_raw_id": "afc69645f8b84b56a20532dbdde78f56",
    "title": "Код ДК 021:2015: код ДК 021:2015:31440000-2: Акумуляторні батареї (Акумуляторна батарея Deye RW-M6-1-B 51.2V 120AH)",
    "org": "КОМУНАЛЬНЕ НЕКОМЕРЦІЙНЕ ПІДПРИЄМСТВО \"МІСЬКА ПОЛІКЛІНІКА №24\" ХАРКІВСЬКОЇ МІСЬКОЇ РАДИ",
    "source": "prozorro",
    "platform": "prozorro",
    "type": "BESS",
    "amount": 73440.0,
    "currency": "UAH",
    "deadline": "",
    "cpvs": [
      "31440000-2"
    ],
    "cpv": "31440000-2",
    "status": "new",
    "url": "https://prozorro.gov.ua/tender/afc69645f8b84b56a20532dbdde78f56",
    "is_new": false,
    "score": 75,
    "fetched_at": "2026-03-27T10:30:14.709935"
  },
  {
    "id": "UA-2026-03-20-008036-a",
    "_raw_id": "6eff4295e53545d896ce745b3ea4d6ef",
    "title": "Акумулятор DE-YE SE-F5 Pro-C LifePO4 LV 51.2v 100ah 5.12kwh",
    "org": "КОМУНАЛЬНИЙ ЗАКЛАД \"ЗАКЛАД ДОШКІЛЬНОЇ ОСВІТИ ТУРБІВСЬКИЙ ЯСЛА-САДОК № 2 ТУРБІВСЬКОЇ СЕЛИЩНОЇ РАДИ ВІННИЦЬКОГО РАЙОНУ ВІННИЦЬКОЇ ОБЛАСТІ\"",
    "source": "prozorro",
    "platform": "prozorro",
    "type": "BESS",
    "amount": 85000.0,
    "currency": "UAH",
    "deadline": "",
    "cpvs": [
      "31440000-2"
    ],
    "cpv": "31440000-2",
    "status": "new",
    "url": "https://prozorro.gov.ua/tender/6eff4295e53545d896ce745b3ea4d6ef",
    "is_new": false,
    "score": 75,
    "fetched_at": "2026-03-27T10:45:49.007435"
  },
  {
    "id": "UA-2026-03-20-005655-a",
    "_raw_id": "71bc0ec99d1b4ba69a507123fcb56142",
    "title": "Зовнішня батарея для ДБЖ/інвертора",
    "org": "Дитяча музична школа с.Щасливе Пристоличної сільської ради",
    "source": "prozorro",
    "platform": "prozorro",
    "type": "BESS",
    "amount": 68000.0,
    "currency": "UAH",
    "deadline": "",
    "cpvs": [
      "31440000-2"
    ],
    "cpv": "31440000-2",
    "status": "new",
    "url": "https://prozorro.gov.ua/tender/71bc0ec99d1b4ba69a507123fcb56142",
    "is_new": false,
    "score": 75,
    "fetched_at": "2026-03-27T11:09:47.034858"
  },
  {
    "id": "UA-2026-03-31-004242-a",
    "_raw_id": "b56299d66f3e44b4bb260e69c0c789ca",
    "title": "Зарядний пристрій LiFeR для акумуляторів 24В 70А LiFePO4 або еквівалент",
    "org": "Військова частина А5100",
    "source": "prozorro",
    "platform": "prozorro",
    "type": "BESS",
    "amount": 507000.0,
    "currency": "UAH",
    "deadline": "2026-04-08",
    "cpvs": [
      "31150000-2"
    ],
    "cpv": "31150000-2",
    "status": "urgent",
    "url": "https://prozorro.gov.ua/tender/b56299d66f3e44b4bb260e69c0c789ca",
    "is_new": false,
    "score": 75,
    "fetched_at": "2026-04-08T06:08:10.419373"
  },
  {
    "id": "UA-2026-03-23-004336-a",
    "_raw_id": "8a3bead271334f8fa072b78d77d5cb22",
    "title": "31155000-7 — Інвертори (Гібридний інвертор SUN-6K-SG05LP1-EU-AM2-P (або еквівалент) для потреб ЗСУ)",
    "org": "Департамент оборонної роботи, забезпечення законності та правопорядку Сумської обласної державної адміністрації ",
    "source": "prozorro",
    "platform": "prozorro",
    "type": "Inverter",
    "amount": 366383.0,
    "currency": "UAH",
    "deadline": "2026-04-06",
    "cpvs": [
      "31155000-7"
    ],
    "cpv": "31155000-7",
    "status": "urgent",
    "url": "https://prozorro.gov.ua/tender/8a3bead271334f8fa072b78d77d5cb22",
    "is_new": true,
    "score": 75,
    "fetched_at": "2026-04-08T11:03:53.265084"
  },
  {
    "id": "UA-2026-04-08-002370-a",
    "_raw_id": "d3975af40bd3423c80e286639325fba2",
    "title": "Батареї акумуляторні для джерела безперебійного живлення APC SMART UPS SRT-6000 (SRT6KRMXLI)",
    "org": "ХАРКІВСЬКА МИТНИЦЯ",
    "source": "prozorro",
    "platform": "prozorro",
    "type": "BESS",
    "amount": 32551.92,
    "currency": "UAH",
    "deadline": "2026-04-16",
    "cpvs": [
      "31440000-2"
    ],
    "cpv": "31440000-2",
    "status": "active",
    "url": "https://prozorro.gov.ua/tender/d3975af40bd3423c80e286639325fba2",
    "is_new": true,
    "score": 75,
    "fetched_at": "2026-04-08T11:30:16.383355"
  },
  {
    "id": "UA-2026-03-20-007871-a",
    "_raw_id": "2081d6a87b5a4cc78c13301d8eb1115e",
    "title": "Інвертори подвійного перетворювання  згідно ДК 021:2015 код 31150000-2 Баласти для розрядних ламп чи трубок",
    "org": "КОНЦЕРН “МІСЬКІ ТЕПЛОВІ МЕРЕЖІ”",
    "source": "prozorro",
    "platform": "prozorro",
    "type": "Inverter",
    "amount": 426000.0,
    "currency": "UAH",
    "deadline": "2026-04-01",
    "cpvs": [
      "31155000-7"
    ],
    "cpv": "31155000-7",
    "status": "active",
    "url": "https://prozorro.gov.ua/tender/2081d6a87b5a4cc78c13301d8eb1115e",
    "is_new": false,
    "score": 70,
    "fetched_at": "2026-03-27T10:41:56.438324"
  },
  {
    "id": "UA-2026-03-20-007874-a",
    "_raw_id": "94f98f6df92845f3a25eeb369a02a2a5",
    "title": "Інвертор SUN-6K-SG05LP1-EU",
    "org": "КОМУНАЛЬНИЙ ЗАКЛАД \"ЗАКЛАД ДОШКІЛЬНОЇ ОСВІТИ ТУРБІВСЬКИЙ ЯСЛА-САДОК № 2 ТУРБІВСЬКОЇ СЕЛИЩНОЇ РАДИ ВІННИЦЬКОГО РАЙОНУ ВІННИЦЬКОЇ ОБЛАСТІ\"",
    "source": "prozorro",
    "platform": "prozorro",
    "type": "Inverter",
    "amount": 43290.0,
    "currency": "UAH",
    "deadline": "",
    "cpvs": [
      "31155000-7"
    ],
    "cpv": "31155000-7",
    "status": "new",
    "url": "https://prozorro.gov.ua/tender/94f98f6df92845f3a25eeb369a02a2a5",
    "is_new": false,
    "score": 70,
    "fetched_at": "2026-03-27T10:42:09.603840"
  },
  {
    "id": "UA-2026-03-20-008865-a",
    "_raw_id": "baec252dd5ab4e61bc61f95063f132f6",
    "title": "Акумуляторні батареї",
    "org": "8 державний пожежно-рятувальний загін Головного управління Державної служби України з надзвичайних ситуацій у Львівській області",
    "source": "prozorro",
    "platform": "prozorro",
    "type": "BESS",
    "amount": 34050.0,
    "currency": "UAH",
    "deadline": "",
    "cpvs": [
      "31440000-2"
    ],
    "cpv": "31440000-2",
    "status": "new",
    "url": "https://prozorro.gov.ua/tender/baec252dd5ab4e61bc61f95063f132f6",
    "is_new": false,
    "score": 70,
    "fetched_at": "2026-03-27T10:54:32.243176"
  },
  {
    "id": "UA-2026-03-20-009217-a",
    "_raw_id": "4dd0e9d543394ee7b665ab61fef3219e",
    "title": "Акумуляторна батарея, код ДК 021:2015: 31440000-2 – Акумуляторні батареї",
    "org": "ХМЕЛЬНИЦЬКЕ МІСЬКЕ  КОМУНАЛЬНЕ ПІДПРИЄМСТВО \"ХМЕЛЬНИЦЬКІНФОЦЕНТР\"",
    "source": "prozorro",
    "platform": "prozorro",
    "type": "BESS",
    "amount": 5490.0,
    "currency": "UAH",
    "deadline": "",
    "cpvs": [
      "31440000-2"
    ],
    "cpv": "31440000-2",
    "status": "new",
    "url": "https://prozorro.gov.ua/tender/4dd0e9d543394ee7b665ab61fef3219e",
    "is_new": false,
    "score": 70,
    "fetched_at": "2026-03-27T10:58:35.468656"
  },
  {
    "id": "UA-2026-03-20-009934-a",
    "_raw_id": "9609c6e546274b0ba795cce4c1a9dcb7",
    "title": "Блок живлення, Акумуляторна батарея",
    "org": "КОМУНАЛЬНЕ НЕКОМЕРЦІЙНЕ ПІДПРИЄМСТВО \"КЛІНІКА \"СІМЕЙНИЙ ЛІКАР\" ШИРОКІВСЬКОЇ СІЛЬСЬКОЇ РАДИ ЗАПОРІЗЬКОГО РАЙОНУ ЗАПОРІЗЬКОЇ ОБЛАСТІ",
    "source": "prozorro",
    "platform": "prozorro",
    "type": "BESS",
    "amount": 6600.0,
    "currency": "UAH",
    "deadline": "",
    "cpvs": [
      "31150000-2"
    ],
    "cpv": "31150000-2",
    "status": "new",
    "url": "https://prozorro.gov.ua/tender/9609c6e546274b0ba795cce4c1a9dcb7",
    "is_new": false,
    "score": 70,
    "fetched_at": "2026-03-27T11:07:19.733684"
  },
  {
    "id": "UA-2026-03-20-009117-a",
    "_raw_id": "5cc0d112a89f4ea5a6aae32e23f5a47d",
    "title": "Акумуляторна батарея",
    "org": "Комунальне підприємство \"Теплоенерго\" Кременчуцької міської ради Кременчуцького району Полтавської області",
    "source": "prozorro",
    "platform": "prozorro",
    "type": "BESS",
    "amount": 750.0,
    "currency": "UAH",
    "deadline": "",
    "cpvs": [
      "31440000-2"
    ],
    "cpv": "31440000-2",
    "status": "new",
    "url": "https://prozorro.gov.ua/tender/5cc0d112a89f4ea5a6aae32e23f5a47d",
    "is_new": false,
    "score": 70,
    "fetched_at": "2026-03-27T11:07:39.406620"
  },
  {
    "id": "UA-2026-03-20-010078-a",
    "_raw_id": "ed91183f842b46fcbddc2be2e4211ace",
    "title": "Придбання матеріалів для проведення ремонтних робіт господарським способом (31440000-2 Акумуляторні батареї)",
    "org": "ЖИТЛОВО-КОМУНАЛЬНЕ ПІДПРИЄМСТВО \"КОМУНАЛЬНИК\"",
    "source": "prozorro",
    "platform": "prozorro",
    "type": "BESS",
    "amount": 4350.0,
    "currency": "UAH",
    "deadline": "",
    "cpvs": [
      "31440000-2"
    ],
    "cpv": "31440000-2",
    "status": "new",
    "url": "https://prozorro.gov.ua/tender/ed91183f842b46fcbddc2be2e4211ace",
    "is_new": false,
    "score": 70,
    "fetched_at": "2026-03-27T11:07:53.238220"
  },
  {
    "id": "UA-2026-03-20-010397-a",
    "_raw_id": "812211ccbbc94322afecd1b8999258e4",
    "title": "Акумулятор. ДК 021-2015 (CPV) 31440000-2 - Акумуляторні батареї",
    "org": "Ганнівський ліцей Петрівської селищної ради Олександрійського району Кіровоградської області",
    "source": "prozorro",
    "platform": "prozorro",
    "type": "BESS",
    "amount": 21600.0,
    "currency": "UAH",
    "deadline": "",
    "cpvs": [
      "31440000-2"
    ],
    "cpv": "31440000-2",
    "status": "new",
    "url": "https://prozorro.gov.ua/tender/812211ccbbc94322afecd1b8999258e4",
    "is_new": false,
    "score": 70,
    "fetched_at": "2026-03-27T11:13:39.000709"
  },
  {
    "id": "UA-2026-03-20-010903-a",
    "_raw_id": "b1ab2904a540456badeb3e57952b5ca5",
    "title": "Електричні акумулятори",
    "org": "Військова частина А7047",
    "source": "prozorro",
    "platform": "prozorro",
    "type": "BESS",
    "amount": 0,
    "currency": "UAH",
    "deadline": "",
    "cpvs": [
      "31440000-2"
    ],
    "cpv": "31440000-2",
    "status": "new",
    "url": "https://prozorro.gov.ua/tender/b1ab2904a540456badeb3e57952b5ca5",
    "is_new": false,
    "score": 70,
    "fetched_at": "2026-03-27T11:17:21.667920"
  },
  {
    "id": "UA-2026-03-20-010998-a",
    "_raw_id": "4e39a131d6014ea6a7610725a2ec079b",
    "title": "Електричні акумулятори",
    "org": "Військова частина А7047",
    "source": "prozorro",
    "platform": "prozorro",
    "type": "BESS",
    "amount": 0,
    "currency": "UAH",
    "deadline": "",
    "cpvs": [
      "31440000-2"
    ],
    "cpv": "31440000-2",
    "status": "new",
    "url": "https://prozorro.gov.ua/tender/4e39a131d6014ea6a7610725a2ec079b",
    "is_new": false,
    "score": 70,
    "fetched_at": "2026-03-27T11:18:34.636935"
  },
  {
    "id": "UA-2026-04-07-014671-a",
    "_raw_id": "44631e6c02754a7985c3bc3337859f11",
    "title": "Акумуляторна батарея",
    "org": "ВИКОНАВЧИЙ КОМІТЕТ НАБУТІВСЬКОЇ СІЛЬСЬКОЇ РАДИ ЧЕРКАСЬКОГО РАЙОНУ ЧЕРКАСЬКОЇ ОБЛАСТІ",
    "source": "prozorro",
    "platform": "prozorro",
    "type": "BESS",
    "amount": 47158.98,
    "currency": "UAH",
    "deadline": "",
    "cpvs": [
      "31440000-2"
    ],
    "cpv": "31440000-2",
    "status": "new",
    "url": "https://prozorro.gov.ua/tender/44631e6c02754a7985c3bc3337859f11",
    "is_new": false,
    "score": 70,
    "fetched_at": "2026-04-08T05:51:29.656569"
  },
  {
    "id": "UA-2026-04-06-009842-a",
    "_raw_id": "93ef1c496b5c4582a56614e5535b6617",
    "title": "Акумуляторні батареї",
    "org": "АКЦІОНЕРНЕ ТОВАРИСТВО \"НАУКОВО-ВИРОБНИЧИЙ КОМПЛЕКС ГАЗОТУРБОБУДУВАННЯ \"ЗОРЯ\" - \"МАШПРОЕКТ\"",
    "source": "prozorro",
    "platform": "prozorro",
    "type": "BESS",
    "amount": 2265000.0,
    "currency": "UAH",
    "deadline": "2026-04-15",
    "cpvs": [
      "31440000-2"
    ],
    "cpv": "31440000-2",
    "status": "active",
    "url": "https://prozorro.gov.ua/tender/93ef1c496b5c4582a56614e5535b6617",
    "is_new": false,
    "score": 70,
    "fetched_at": "2026-04-08T05:54:56.421084"
  },
  {
    "id": "UA-2026-03-31-008063-a",
    "_raw_id": "89c563f9c2d849a98d6aa77117ffa3d8",
    "title": "Закупівля джерела безперебійного живлення (система зберігання енергії) код CPV за ЄЗС ДК 021:2015: 31150000-2 Баласти для розрядних ламп чи трубок (31154000-0 Джерела безперебійного живлення)",
    "org": "ДЕРЖАВНА УСТАНОВА \"ЦЕНТР ІНФРАСТРУКТУРИ ТА ТЕХНОЛОГІЙ МІНІСТЕРСТВА ВНУТРІШНІХ СПРАВ УКРАЇНИ\"",
    "source": "prozorro",
    "platform": "prozorro",
    "type": "Other",
    "amount": 1944044.0,
    "currency": "UAH",
    "deadline": "2026-04-08",
    "cpvs": [
      "31150000-2"
    ],
    "cpv": "31150000-2",
    "status": "urgent",
    "url": "https://prozorro.gov.ua/tender/89c563f9c2d849a98d6aa77117ffa3d8",
    "is_new": false,
    "score": 70,
    "fetched_at": "2026-04-08T06:11:10.619862"
  },
  {
    "id": "UA-2026-03-28-000138-a",
    "_raw_id": "8e3e73a7e70a4128b0d0395d3d18ffb9",
    "title": "Акумуляторні батареї",
    "org": "20 БРИГАДА ОПЕРАТИВНОГО ПРИЗНАЧЕННЯ НАЦІОНАЛЬНОЇ ГВАРДІЇ УКРАЇНИ (ВІЙСЬКОВА ЧАСТИНА 3009)",
    "source": "prozorro",
    "platform": "prozorro",
    "type": "BESS",
    "amount": 290893.99,
    "currency": "UAH",
    "deadline": "2026-04-08",
    "cpvs": [
      "31440000-2"
    ],
    "cpv": "31440000-2",
    "status": "urgent",
    "url": "https://prozorro.gov.ua/tender/8e3e73a7e70a4128b0d0395d3d18ffb9",
    "is_new": false,
    "score": 70,
    "fetched_at": "2026-04-08T06:11:47.240175"
  },
  {
    "id": "UA-2026-03-31-011453-a",
    "_raw_id": "a825756a94e948d58db794e671516a83",
    "title": "Акумуляторні батареї",
    "org": "Департамент патрульної поліції",
    "source": "prozorro",
    "platform": "prozorro",
    "type": "BESS",
    "amount": 97714.67,
    "currency": "UAH",
    "deadline": "2026-04-08",
    "cpvs": [
      "31440000-2"
    ],
    "cpv": "31440000-2",
    "status": "urgent",
    "url": "https://prozorro.gov.ua/tender/a825756a94e948d58db794e671516a83",
    "is_new": false,
    "score": 70,
    "fetched_at": "2026-04-08T06:15:34.977502"
  },
  {
    "id": "UA-2026-04-08-001467-a",
    "_raw_id": "b67d8aa344764db7bfedb680b27404a5",
    "title": "акумулятрона батарея (ДК 021:2015: 31440000-2 акумуляторні батареї)",
    "org": "1 ДЕРЖАВНИЙ ПОЖЕЖНО-РЯТУВАЛЬНИЙ ЗАГІН ГОЛОВНОГО УПРАВЛІННЯ ДЕРЖАВНОЇ СЛУЖБИ УКРАЇНИ З НАДЗВИЧАЙНИХ СИТУАЦІЙ У ВІННИЦЬКІЙ ОБЛАСТІ",
    "source": "prozorro",
    "platform": "prozorro",
    "type": "BESS",
    "amount": 4568.4,
    "currency": "UAH",
    "deadline": "",
    "cpvs": [
      "31440000-2"
    ],
    "cpv": "31440000-2",
    "status": "new",
    "url": "https://prozorro.gov.ua/tender/b67d8aa344764db7bfedb680b27404a5",
    "is_new": true,
    "score": 70,
    "fetched_at": "2026-04-08T11:06:17.224411"
  },
  {
    "id": "UA-2026-04-08-001885-a",
    "_raw_id": "8a5bd2579ef44f8399a1ccde8d5f171c",
    "title": " Гібридний інвентор Deye SUN-6K-SG05LP1-EU-AM2-P.",
    "org": "СОЦІАЛЬНО-ГУМАНІТАРНИЙ ВІДДІЛ ОПІШНЯНСЬКОЇ СЕЛИЩНОЇ РАДИ",
    "source": "prozorro",
    "platform": "prozorro",
    "type": "Other",
    "amount": 46840.0,
    "currency": "UAH",
    "deadline": "",
    "cpvs": [
      "31150000-2"
    ],
    "cpv": "31150000-2",
    "status": "new",
    "url": "https://prozorro.gov.ua/tender/8a5bd2579ef44f8399a1ccde8d5f171c",
    "is_new": true,
    "score": 70,
    "fetched_at": "2026-04-08T11:18:16.527475"
  },
  {
    "id": "UA-2026-04-08-002062-a",
    "_raw_id": "c07473d7375c4ebe95884271d1c72a4c",
    "title": "Акумуляторні батареї ",
    "org": "Київський національний університет імені Тараса Шевченка",
    "source": "prozorro",
    "platform": "prozorro",
    "type": "BESS",
    "amount": 91998.0,
    "currency": "UAH",
    "deadline": "",
    "cpvs": [
      "31440000-2"
    ],
    "cpv": "31440000-2",
    "status": "new",
    "url": "https://prozorro.gov.ua/tender/c07473d7375c4ebe95884271d1c72a4c",
    "is_new": true,
    "score": 70,
    "fetched_at": "2026-04-08T11:23:10.754007"
  },
  {
    "id": "UA-2026-04-08-002081-a",
    "_raw_id": "22cd11777f7a49bca39edb52e1ce5322",
    "title": "Акумуляторні батареї",
    "org": "Державний навчальний заклад \"Шумське професійно-технічне училище\"",
    "source": "prozorro",
    "platform": "prozorro",
    "type": "BESS",
    "amount": 9000.0,
    "currency": "UAH",
    "deadline": "",
    "cpvs": [
      "31440000-2"
    ],
    "cpv": "31440000-2",
    "status": "new",
    "url": "https://prozorro.gov.ua/tender/22cd11777f7a49bca39edb52e1ce5322",
    "is_new": true,
    "score": 70,
    "fetched_at": "2026-04-08T11:24:58.715980"
  },
  {
    "id": "UA-2026-04-08-002740-a",
    "_raw_id": "c25a9971f35a484ab29495095abc3bfa",
    "title": "Акумуляторна батарея",
    "org": "Державна установа \"Кагарлицька виправна колонія (№115)\"",
    "source": "prozorro",
    "platform": "prozorro",
    "type": "BESS",
    "amount": 4890.0,
    "currency": "UAH",
    "deadline": "",
    "cpvs": [
      "31440000-2"
    ],
    "cpv": "31440000-2",
    "status": "new",
    "url": "https://prozorro.gov.ua/tender/c25a9971f35a484ab29495095abc3bfa",
    "is_new": true,
    "score": 70,
    "fetched_at": "2026-04-08T11:39:54.809749"
  },
  {
    "id": "UA-2026-04-08-002795-a",
    "_raw_id": "8d0cb21176954bb6a81f9b0a92a12f56",
    "title": "Акумулятор Forse 6CT-74. 720A EN за кодом ЄЗС ДК 021:2015 31440000-2 акумуляторні батареї.",
    "org": "Недригайлівська селищна рада",
    "source": "prozorro",
    "platform": "prozorro",
    "type": "BESS",
    "amount": 3800.0,
    "currency": "UAH",
    "deadline": "",
    "cpvs": [
      "31440000-2"
    ],
    "cpv": "31440000-2",
    "status": "new",
    "url": "https://prozorro.gov.ua/tender/8d0cb21176954bb6a81f9b0a92a12f56",
    "is_new": true,
    "score": 70,
    "fetched_at": "2026-04-08T11:41:28.019680"
  },
  {
    "id": "UA-2026-03-11-009316-a",
    "_raw_id": "7fad1110eac241ee8d461dfe982b6d0e",
    "title": "СИСТЕМИ БЕЗПЕРЕБІЙНОГО ЖИВЛЕННЯ ТИП 1, СИСТЕМИ БЕЗПЕРЕБІЙНОГО ЖИВЛЕННЯ ТИП 2",
    "org": "Відділ освіти  Нововодолазької селищної ради",
    "source": "prozorro",
    "platform": "prozorro",
    "type": "BESS",
    "amount": 2266000.0,
    "currency": "UAH",
    "deadline": "2026-03-19",
    "cpvs": [
      "31154000-0"
    ],
    "cpv": "31154000-0",
    "status": "urgent",
    "url": "https://prozorro.gov.ua/tender/7fad1110eac241ee8d461dfe982b6d0e",
    "is_new": false,
    "score": 65,
    "fetched_at": "2026-03-27T10:27:17.206958"
  },
  {
    "id": "UA-2026-03-20-007214-a",
    "_raw_id": "ecc9392f4a2d4e53983ea323655d3648",
    "title": "Акамуляторна батарея",
    "org": "ВІДДІЛ ОСВІТИ, МОЛОДІ ТА СПОРТУ ЛЮБОМЛЬСЬКОЇ МІСЬКОЇ РАДИ",
    "source": "prozorro",
    "platform": "prozorro",
    "type": "BESS",
    "amount": 5000.0,
    "currency": "UAH",
    "deadline": "",
    "cpvs": [
      "31440000-2"
    ],
    "cpv": "31440000-2",
    "status": "new",
    "url": "https://prozorro.gov.ua/tender/ecc9392f4a2d4e53983ea323655d3648",
    "is_new": false,
    "score": 65,
    "fetched_at": "2026-03-27T10:34:04.149998"
  },
  {
    "id": "UA-2026-03-20-008540-a",
    "_raw_id": "b378e36e700c4a92ac5ca673140fceb5",
    "title": "Джерело безперебійного живлення",
    "org": "Управління культури і туризму Білоцерківської міської ради",
    "source": "prozorro",
    "platform": "prozorro",
    "type": "Other",
    "amount": 12800.0,
    "currency": "UAH",
    "deadline": "",
    "cpvs": [
      "31150000-2"
    ],
    "cpv": "31150000-2",
    "status": "new",
    "url": "https://prozorro.gov.ua/tender/b378e36e700c4a92ac5ca673140fceb5",
    "is_new": false,
    "score": 65,
    "fetched_at": "2026-03-27T10:49:59.259848"
  },
  {
    "id": "UA-2026-03-20-008999-a",
    "_raw_id": "d935ffe077d34ae49848ec2faf1adf32",
    "title": "ДК 021:2015, код 31150000-2 Баласти для розрядних ламп чи трубок",
    "org": "Комунальне некомерційне підприємство \"Іллінецька міська лікарня\" Іллінецької міської ради\n",
    "source": "prozorro",
    "platform": "prozorro",
    "type": "Other",
    "amount": 400.0,
    "currency": "UAH",
    "deadline": "",
    "cpvs": [
      "31150000-2"
    ],
    "cpv": "31150000-2",
    "status": "new",
    "url": "https://prozorro.gov.ua/tender/d935ffe077d34ae49848ec2faf1adf32",
    "is_new": false,
    "score": 65,
    "fetched_at": "2026-03-27T10:55:43.719144"
  },
  {
    "id": "UA-2026-02-28-000139-a",
    "_raw_id": "1f889412661e4825a58d3701ff4467d7",
    "title": "Джерело безперебійного живлення",
    "org": "Державний центр кіберзахисту Державної служби спеціального зв’язку та захисту інформації України",
    "source": "prozorro",
    "platform": "prozorro",
    "type": "Other",
    "amount": 10000.0,
    "currency": "UAH",
    "deadline": "2026-03-10",
    "cpvs": [
      "31150000-2"
    ],
    "cpv": "31150000-2",
    "status": "urgent",
    "url": "https://prozorro.gov.ua/tender/1f889412661e4825a58d3701ff4467d7",
    "is_new": false,
    "score": 65,
    "fetched_at": "2026-03-27T11:08:49.926003"
  },
  {
    "id": "UA-2026-02-25-011482-a",
    "_raw_id": "7e94974d609e49868bad3871d1289c12",
    "title": "Джерела безперебійного живлення",
    "org": "Головне управління Пенсійного фонду України у Вінницькій області",
    "source": "prozorro",
    "platform": "prozorro",
    "type": "Other",
    "amount": 1202733.33,
    "currency": "UAH",
    "deadline": "2026-03-05",
    "cpvs": [
      "31150000-2"
    ],
    "cpv": "31150000-2",
    "status": "urgent",
    "url": "https://prozorro.gov.ua/tender/7e94974d609e49868bad3871d1289c12",
    "is_new": false,
    "score": 65,
    "fetched_at": "2026-03-27T11:14:28.564820"
  },
  {
    "id": "UA-2026-03-20-010706-a",
    "_raw_id": "2b099fd07e7440d98c25e60e5e789889",
    "title": "Баласти для розрядних ламп чи трубок",
    "org": "КП\"Тетіївводоканал\"",
    "source": "prozorro",
    "platform": "prozorro",
    "type": "Other",
    "amount": 1450000.0,
    "currency": "UAH",
    "deadline": "2026-03-30",
    "cpvs": [
      "31150000-2"
    ],
    "cpv": "31150000-2",
    "status": "active",
    "url": "https://prozorro.gov.ua/tender/2b099fd07e7440d98c25e60e5e789889",
    "is_new": false,
    "score": 65,
    "fetched_at": "2026-03-27T11:16:47.245669"
  },
  {
    "id": "UA-2026-03-27-006834-a",
    "_raw_id": "dfea1ac005154718b0d043ac65770ee1",
    "title": "Портативні електростанції для потреб Вищого антикорупційного суду",
    "org": "ВИЩИЙ АНТИКОРУПЦІЙНИЙ СУД",
    "source": "prozorro",
    "platform": "prozorro",
    "type": "Inverter",
    "amount": 650000.0,
    "currency": "UAH",
    "deadline": "2026-04-05",
    "cpvs": [
      "31155000-7"
    ],
    "cpv": "31155000-7",
    "status": "urgent",
    "url": "https://prozorro.gov.ua/tender/dfea1ac005154718b0d043ac65770ee1",
    "is_new": false,
    "score": 65,
    "fetched_at": "2026-04-08T05:49:46.843356"
  },
  {
    "id": "UA-2026-04-07-014619-a",
    "_raw_id": "b9961dd22e434cfd85c688161d3452bf",
    "title": "Пристрій безперебійного живлення пJоу",
    "org": "ВИКОНАВЧИЙ КОМІТЕТ НАБУТІВСЬКОЇ СІЛЬСЬКОЇ РАДИ ЧЕРКАСЬКОГО РАЙОНУ ЧЕРКАСЬКОЇ ОБЛАСТІ",
    "source": "prozorro",
    "platform": "prozorro",
    "type": "Other",
    "amount": 13046.04,
    "currency": "UAH",
    "deadline": "",
    "cpvs": [
      "31150000-2"
    ],
    "cpv": "31150000-2",
    "status": "new",
    "url": "https://prozorro.gov.ua/tender/b9961dd22e434cfd85c688161d3452bf",
    "is_new": false,
    "score": 65,
    "fetched_at": "2026-04-08T05:50:23.246808"
  },
  {
    "id": "UA-2026-04-01-009569-a",
    "_raw_id": "9b41c5b85da94954a1ba92a63dfcdc58",
    "title": "Врізна металева зарядка в авто USB + Type-C 65W + Вольтметр + Амперметр + Швидке заряджання, 12-24В Синє підсвічування  або еквівалент",
    "org": "Військова частина А5100",
    "source": "prozorro",
    "platform": "prozorro",
    "type": "Other",
    "amount": 17386.8,
    "currency": "UAH",
    "deadline": "2026-04-10",
    "cpvs": [
      "31150000-2"
    ],
    "cpv": "31150000-2",
    "status": "active",
    "url": "https://prozorro.gov.ua/tender/9b41c5b85da94954a1ba92a63dfcdc58",
    "is_new": false,
    "score": 65,
    "fetched_at": "2026-04-08T05:58:51.065051"
  },
  {
    "id": "UA-2026-03-27-007407-a",
    "_raw_id": "57483ce858ab4194b6691f35440c045f",
    "title": "Придбання та встановлення стаціонарних систем накопичення енергії для КЗДО №20",
    "org": "ВІДДІЛ ОСВІТИ ВИКОНКОМУ ПОКРОВСЬКОЇ РАЙОННОЇ В МІСТІ РАДИ",
    "source": "prozorro",
    "platform": "prozorro",
    "type": "Other",
    "amount": 441000.0,
    "currency": "UAH",
    "deadline": "2026-04-08",
    "cpvs": [
      "31150000-2"
    ],
    "cpv": "31150000-2",
    "status": "urgent",
    "url": "https://prozorro.gov.ua/tender/57483ce858ab4194b6691f35440c045f",
    "is_new": false,
    "score": 65,
    "fetched_at": "2026-04-08T06:00:28.972214"
  },
  {
    "id": "UA-2026-03-27-007828-a",
    "_raw_id": "a8b2801fadb64f9a8a6e8c748cf20928",
    "title": "Придбання та встановлення стаціонарних систем накопичення енергії для КЗДО №175",
    "org": "ВІДДІЛ ОСВІТИ ВИКОНКОМУ ПОКРОВСЬКОЇ РАЙОННОЇ В МІСТІ РАДИ",
    "source": "prozorro",
    "platform": "prozorro",
    "type": "Other",
    "amount": 441000.0,
    "currency": "UAH",
    "deadline": "2026-04-08",
    "cpvs": [
      "31150000-2"
    ],
    "cpv": "31150000-2",
    "status": "urgent",
    "url": "https://prozorro.gov.ua/tender/a8b2801fadb64f9a8a6e8c748cf20928",
    "is_new": false,
    "score": 65,
    "fetched_at": "2026-04-08T06:10:06.850093"
  },
  {
    "id": "UA-2026-03-31-007967-a",
    "_raw_id": "485a0d3fa73443188e1c78820a903ee8",
    "title": "Зарядна станція “EcoFlow DELTA 3 Max»  (або еквівалент) код ДК 021:2015:31154000-0 «Джерела безперебійного живлення»",
    "org": "Дар’ївська сільська рада Херсонського району Херсонської області",
    "source": "prozorro",
    "platform": "prozorro",
    "type": "BESS",
    "amount": 600000.0,
    "currency": "UAH",
    "deadline": "2026-04-08",
    "cpvs": [
      "31154000-0"
    ],
    "cpv": "31154000-0",
    "status": "urgent",
    "url": "https://prozorro.gov.ua/tender/485a0d3fa73443188e1c78820a903ee8",
    "is_new": false,
    "score": 65,
    "fetched_at": "2026-04-08T06:11:30.143481"
  },
  {
    "id": "UA-2026-03-27-007674-a",
    "_raw_id": "8ba7d975b7be40dd82ac74b55f006eb7",
    "title": "Придбання та встановлення стаціонарних систем накопичення енергії для КЗДО №243",
    "org": "ВІДДІЛ ОСВІТИ ВИКОНКОМУ ПОКРОВСЬКОЇ РАЙОННОЇ В МІСТІ РАДИ",
    "source": "prozorro",
    "platform": "prozorro",
    "type": "Other",
    "amount": 441000.0,
    "currency": "UAH",
    "deadline": "2026-04-08",
    "cpvs": [
      "31150000-2"
    ],
    "cpv": "31150000-2",
    "status": "urgent",
    "url": "https://prozorro.gov.ua/tender/8ba7d975b7be40dd82ac74b55f006eb7",
    "is_new": false,
    "score": 65,
    "fetched_at": "2026-04-08T06:13:05.058790"
  },
  {
    "id": "UA-2026-03-31-001858-a",
    "_raw_id": "edb2fafba8f14470b88ab3d70a2fbea7",
    "title": "Системи безперебійного живлення за ДК 021:2015 31150000-2 Баласти для розрядних ламп чи трубок  (31154000-0  Джерела безперебійного живлення) (придбання та встановлення джерел резервного живлення)",
    "org": "Відділ освіти, молоді та спорту П’ятихатської міської ради",
    "source": "prozorro",
    "platform": "prozorro",
    "type": "BESS",
    "amount": 1438760.0,
    "currency": "UAH",
    "deadline": "2026-04-08",
    "cpvs": [
      "31154000-0"
    ],
    "cpv": "31154000-0",
    "status": "urgent",
    "url": "https://prozorro.gov.ua/tender/edb2fafba8f14470b88ab3d70a2fbea7",
    "is_new": false,
    "score": 65,
    "fetched_at": "2026-04-08T06:14:16.741083"
  },
  {
    "id": "UA-2026-04-08-000369-a",
    "_raw_id": "062a1ea4b94e471f841f0350aa3cea77",
    "title": "Джерела безперебійного живлення (ДК 021:2015: 31154000-0-Джерела безперебійного живлення)",
    "org": "Комунальна Установа \"Мачухівський центр культури, дозвілля та бібліотечних послуг\" Мачухівської сільської ради Полтавського району Полтавської області",
    "source": "prozorro",
    "platform": "prozorro",
    "type": "BESS",
    "amount": 3226.0,
    "currency": "UAH",
    "deadline": "",
    "cpvs": [
      "31154000-0"
    ],
    "cpv": "31154000-0",
    "status": "new",
    "url": "https://prozorro.gov.ua/tender/062a1ea4b94e471f841f0350aa3cea77",
    "is_new": true,
    "score": 65,
    "fetched_at": "2026-04-08T10:28:47.417767"
  },
  {
    "id": "UA-2026-04-02-006777-a",
    "_raw_id": "75eb85574f9c42709448ed1207deb82e",
    "title": "Джерело безперебійного живлення для потреб зв’язку спеціального призначення",
    "org": "Управління Державної служби спеціального зв'язку та захисту інформації України в Кіровоградській області",
    "source": "prozorro",
    "platform": "prozorro",
    "type": "Other",
    "amount": 60000.0,
    "currency": "UAH",
    "deadline": "2026-04-11",
    "cpvs": [
      "31150000-2"
    ],
    "cpv": "31150000-2",
    "status": "active",
    "url": "https://prozorro.gov.ua/tender/75eb85574f9c42709448ed1207deb82e",
    "is_new": true,
    "score": 65,
    "fetched_at": "2026-04-08T10:32:34.405463"
  },
  {
    "id": "UA-2026-03-31-008335-a",
    "_raw_id": "d581b4235ddd4a0c8a17817719dee031",
    "title": "Система резервного живлення",
    "org": "Відділ освіти Роменської міської ради Сумської області",
    "source": "prozorro",
    "platform": "prozorro",
    "type": "Other",
    "amount": 126000.0,
    "currency": "UAH",
    "deadline": "2026-04-08",
    "cpvs": [
      "31150000-2"
    ],
    "cpv": "31150000-2",
    "status": "urgent",
    "url": "https://prozorro.gov.ua/tender/d581b4235ddd4a0c8a17817719dee031",
    "is_new": true,
    "score": 65,
    "fetched_at": "2026-04-08T10:32:44.630716"
  },
  {
    "id": "UA-2026-04-02-014322-a",
    "_raw_id": "70d6c2d80cf3408da1f82190d6200e9d",
    "title": "ДК 021:2015 - 31150000-2 - (Зарядний пристрій для «LAZERTAG» С 20)",
    "org": "Військова частина А1890",
    "source": "prozorro",
    "platform": "prozorro",
    "type": "Other",
    "amount": 72500.0,
    "currency": "UAH",
    "deadline": "2026-04-15",
    "cpvs": [
      "31150000-2"
    ],
    "cpv": "31150000-2",
    "status": "active",
    "url": "https://prozorro.gov.ua/tender/70d6c2d80cf3408da1f82190d6200e9d",
    "is_new": true,
    "score": 65,
    "fetched_at": "2026-04-08T11:19:17.764493"
  },
  {
    "id": "UA-2026-04-08-002311-a",
    "_raw_id": "c17c05c0bfe344d785b3cd58b5b375fb",
    "title": "Джерела безперебійного живлення",
    "org": "Комунальне некомерційне підприємство “Центр первинної медико-санітарної допомоги Краснокутської селищної ради” Богодухівського району Харківської області",
    "source": "prozorro",
    "platform": "prozorro",
    "type": "BESS",
    "amount": 25200.0,
    "currency": "UAH",
    "deadline": "",
    "cpvs": [
      "31154000-0"
    ],
    "cpv": "31154000-0",
    "status": "new",
    "url": "https://prozorro.gov.ua/tender/c17c05c0bfe344d785b3cd58b5b375fb",
    "is_new": true,
    "score": 65,
    "fetched_at": "2026-04-08T11:29:04.405582"
  },
  {
    "id": "UA-2026-04-08-002461-a",
    "_raw_id": "23f6bc00d8354a07b08af33429d0943b",
    "title": "Зарядний пристрій",
    "org": "Державна установа \"Кагарлицька виправна колонія (№115)\"",
    "source": "prozorro",
    "platform": "prozorro",
    "type": "Other",
    "amount": 2190.0,
    "currency": "UAH",
    "deadline": "",
    "cpvs": [
      "31150000-2"
    ],
    "cpv": "31150000-2",
    "status": "new",
    "url": "https://prozorro.gov.ua/tender/23f6bc00d8354a07b08af33429d0943b",
    "is_new": true,
    "score": 65,
    "fetched_at": "2026-04-08T11:32:17.110708"
  },
  {
    "id": "UA-2026-04-08-002481-a",
    "_raw_id": "e6bce416de654cce84228af08d1145f0",
    "title": "Джерела безперебійного живлення",
    "org": "ФОНД ДЕРЖАВНОГО МАЙНА УКРАЇНИ",
    "source": "prozorro",
    "platform": "prozorro",
    "type": "BESS",
    "amount": 97510.8,
    "currency": "UAH",
    "deadline": "",
    "cpvs": [
      "31154000-0"
    ],
    "cpv": "31154000-0",
    "status": "new",
    "url": "https://prozorro.gov.ua/tender/e6bce416de654cce84228af08d1145f0",
    "is_new": true,
    "score": 65,
    "fetched_at": "2026-04-08T11:33:31.632134"
  },
  {
    "id": "UA-2026-03-20-008862-a",
    "_raw_id": "f3d2e93123634cfa8fcb366f1763b528",
    "title": "Інверторний генератор",
    "org": "Виконавчий комітет Кременчуцької міської ради Кременчуцького району Полтавської області",
    "source": "prozorro",
    "platform": "prozorro",
    "type": "Inverter",
    "amount": 21900.0,
    "currency": "UAH",
    "deadline": "",
    "cpvs": [
      "31120000-3"
    ],
    "cpv": "31120000-3",
    "status": "new",
    "url": "https://prozorro.gov.ua/tender/f3d2e93123634cfa8fcb366f1763b528",
    "is_new": false,
    "score": 55,
    "fetched_at": "2026-03-27T10:53:58.280830"
  },
  {
    "id": "UA-2026-04-07-014552-a",
    "_raw_id": "996fb3f0e95042b99c1664057ecd62d2",
    "title": "Дизельний інверторний генератор «Könner&Söhnen» KS 6100iDЕ ATSR, дизельний інверторний генератор «Könner&Söhnen» KS 9500iDЕ ATSR",
    "org": "ВІЙСЬКОВА ЧАСТИНА 3018 НАЦІОНАЛЬНОЇ ГВАРДІЇ УКРАЇНИ",
    "source": "prozorro",
    "platform": "prozorro",
    "type": "Inverter",
    "amount": 594100.0,
    "currency": "UAH",
    "deadline": "2026-04-10",
    "cpvs": [
      "31120000-3",
      "31120000-3"
    ],
    "cpv": "31120000-3",
    "status": "active",
    "url": "https://prozorro.gov.ua/tender/996fb3f0e95042b99c1664057ecd62d2",
    "is_new": false,
    "score": 55,
    "fetched_at": "2026-04-08T05:48:57.187691"
  },
  {
    "id": "UA-2026-04-03-010853-a",
    "_raw_id": "966d32959fcb4ec38d240d436a6fc6d1",
    "title": "Інверторний генератор портативний (ДК 021:2015: 31120000-3 — Генератори (відповідний код ДК 021:2015: 31121000-0 – Генераторні установки))",
    "org": "Надвірнянська міська рада",
    "source": "prozorro",
    "platform": "prozorro",
    "type": "Inverter",
    "amount": 70000.0,
    "currency": "UAH",
    "deadline": "2026-04-08",
    "cpvs": [
      "31120000-3",
      "31120000-3"
    ],
    "cpv": "31120000-3",
    "status": "urgent",
    "url": "https://prozorro.gov.ua/tender/966d32959fcb4ec38d240d436a6fc6d1",
    "is_new": false,
    "score": 55,
    "fetched_at": "2026-04-08T06:20:58.760100"
  },
  {
    "id": "UA-2026-03-18-015781-a",
    "_raw_id": "9238f618e620445f804545da9096f43b",
    "title": "Генератори інверторні Scheppach SG3500i 3 кВт",
    "org": "Військова частина А7045",
    "source": "prozorro",
    "platform": "prozorro",
    "type": "Inverter",
    "amount": 539982.0,
    "currency": "UAH",
    "deadline": "2026-03-31",
    "cpvs": [
      "31120000-3"
    ],
    "cpv": "31120000-3",
    "status": "urgent",
    "url": "https://prozorro.gov.ua/tender/9238f618e620445f804545da9096f43b",
    "is_new": false,
    "score": 55,
    "fetched_at": "2026-04-08T06:23:42.180044"
  },
  {
    "id": "UA-2026-03-26-003243-a",
    "_raw_id": "99c77f232d4540939e8da56b482c2cc5",
    "title": "Інверторний генератор Optimat Smart Energy IE3500 або еквівалент",
    "org": "ВІЙСЬКОВА ЧАСТИНА 3036 НАЦІОНАЛЬНОЇ ГВАРДІЇ УКРАЇНИ",
    "source": "prozorro",
    "platform": "prozorro",
    "type": "Inverter",
    "amount": 400000.0,
    "currency": "UAH",
    "deadline": "2026-04-06",
    "cpvs": [
      "31120000-3"
    ],
    "cpv": "31120000-3",
    "status": "urgent",
    "url": "https://prozorro.gov.ua/tender/99c77f232d4540939e8da56b482c2cc5",
    "is_new": false,
    "score": 55,
    "fetched_at": "2026-04-08T06:26:02.136232"
  },
  {
    "id": "UA-2026-04-02-002866-a",
    "_raw_id": "97245ad005c24f289fa827649210308e",
    "title": "Генератор інверторний Könner&Söhnen KS 3300i (3,3 кВт), генератор бензиновий Könner&Söhnen KS7000 (5,5 кВт)",
    "org": "Помічнянська міська рада",
    "source": "prozorro",
    "platform": "prozorro",
    "type": "Inverter",
    "amount": 307687.0,
    "currency": "UAH",
    "deadline": "2026-04-07",
    "cpvs": [
      "31120000-3",
      "31120000-3"
    ],
    "cpv": "31120000-3",
    "status": "urgent",
    "url": "https://prozorro.gov.ua/tender/97245ad005c24f289fa827649210308e",
    "is_new": true,
    "score": 55,
    "fetched_at": "2026-04-08T11:04:12.109052"
  },
  {
    "id": "UA-2026-04-08-002900-a",
    "_raw_id": "61dbf1a3f6ac4a168826a5261e420baf",
    "title": "ДК 021:2015: 31120000-3 — Генератори (Інверторний бензиновий генератор)",
    "org": "Виконавчий комітет Путивльської міської ради",
    "source": "prozorro",
    "platform": "prozorro",
    "type": "Inverter",
    "amount": 232400.0,
    "currency": "UAH",
    "deadline": "2026-04-20",
    "cpvs": [
      "31120000-3"
    ],
    "cpv": "31120000-3",
    "status": "active",
    "url": "https://prozorro.gov.ua/tender/61dbf1a3f6ac4a168826a5261e420baf",
    "is_new": true,
    "score": 55,
    "fetched_at": "2026-04-08T11:45:16.896087"
  },
  {
    "id": "UA-2026-03-27-011787-a",
    "_raw_id": "65a75bc34cd64e27810ffee06072b153",
    "title": "Генератор інверторний бензиновий Hyundai HHY 9050si",
    "org": "Військова частина А4438",
    "source": "prozorro",
    "platform": "prozorro",
    "type": "Inverter",
    "amount": 1295279.2,
    "currency": "UAH",
    "deadline": "2026-04-07",
    "cpvs": [
      "31120000-3"
    ],
    "cpv": "31120000-3",
    "status": "urgent",
    "url": "https://prozorro.gov.ua/tender/65a75bc34cd64e27810ffee06072b153",
    "is_new": true,
    "score": 55,
    "fetched_at": "2026-04-08T11:46:45.299472"
  }
]